roll_regression/__init__.py
roll_regression/roll_regression.dll
roll_regression/roll_regression.py
roll_regression/rust/Cargo.toml
roll_regression/rust/src/lib.rs
roll_regression/rust/src/roll_regression.h
roll_regression/rust/target/release/roll_regression.dll
roll_regression/rust/target/release/deps/nalgebra_macros-2540afb5dca32967.dll
roll_regression/rust/target/release/deps/nalgebra_macros-2540afb5dca32967.dll.lib
roll_regression/rust/target/release/deps/paste-91c39ba77ba90a1b.dll
roll_regression/rust/target/release/deps/paste-91c39ba77ba90a1b.dll.lib
roll_regression/rust/target/x86_64-pc-windows-msvc/release/build/typenum-a5c0047d56a3e91d/out/consts.rs
roll_regression/rust/target/x86_64-pc-windows-msvc/release/build/typenum-a5c0047d56a3e91d/out/op.rs
roll_regression/rust/target/x86_64-pc-windows-msvc/release/build/typenum-a5c0047d56a3e91d/out/tests.rs
roll_regression-0.5.0.dist-info/AUTHORS.rst
roll_regression-0.5.0.dist-info/LICENSE
roll_regression-0.5.0.dist-info/METADATA
roll_regression-0.5.0.dist-info/WHEEL
roll_regression-0.5.0.dist-info/top_level.txt
roll_regression-0.5.0.dist-info/RECORD
